[
{ "rank":0, "start":"Mon_Dec_08_17:39:01_2025","ES_mus": 284, "ES":{"mus":284, "nCalls":1},"PP_mus": 0, "PP":{"mus":0, "nCalls":1},"ES_meta1_mus": 3, "ES_meta1":{"mus":3, "nCalls":1},"ES_meta2_mus": 28, "ES_meta2":{"mus":28, "nCalls":1},"ES_close_mus": 170, "ES_close":{"mus":170, "nCalls":1},"ES_AWD_mus": 81, "ES_AWD":{"mus":81, "nCalls":1}, "databytes":0, "metadatabytes":0, "metametadatabytes":0, "transport_0":{"type":"File_POSIX", "wbytes":4960, "close":{"mus":42, "nCalls":1}, "write":{"mus":37, "nCalls":1}, "open":{"mus":185, "nCalls":1}}, "transport_1":{"type":"File_POSIX", "wbytes":1976, "close":{"mus":19, "nCalls":1}, "write":{"mus":2, "nCalls":5}, "open":{"mus":118, "nCalls":1}} }
]
